<PAMDataset>
  <Metadata domain="IMAGE_STRUCTURE">
    <MDI key="INTERLEAVE">PIXEL</MDI>
  </Metadata>
  <PAMRasterBand band="1">
    <Metadata>
      <MDI key="STATISTICS_APPROXIMATE">YES</MDI>
      <MDI key="STATISTICS_MAXIMUM">231</MDI>
      <MDI key="STATISTICS_MEAN">159.98336588542</MDI>
      <MDI key="STATISTICS_MINIMUM">51</MDI>
      <MDI key="STATISTICS_STDDEV">38.671093426431</MDI>
      <MDI key="STATISTICS_VALID_PERCENT">100</MDI>
    </Metadata>
  </PAMRasterBand>
  <PAMRasterBand band="2">
    <Metadata>
      <MDI key="STATISTICS_APPROXIMATE">YES</MDI>
      <MDI key="STATISTICS_MAXIMUM">213</MDI>
      <MDI key="STATISTICS_MEAN">172.30190429687</MDI>
      <MDI key="STATISTICS_MINIMUM">51</MDI>
      <MDI key="STATISTICS_STDDEV">22.575647202994</MDI>
      <MDI key="STATISTICS_VALID_PERCENT">100</MDI>
    </Metadata>
  </PAMRasterBand>
  <PAMRasterBand band="3">
    <Metadata>
      <MDI key="STATISTICS_APPROXIMATE">YES</MDI>
      <MDI key="STATISTICS_MAXIMUM">241</MDI>
      <MDI key="STATISTICS_MEAN">208.505859375</MDI>
      <MDI key="STATISTICS_MINIMUM">51</MDI>
      <MDI key="STATISTICS_STDDEV">20.615644931171</MDI>
      <MDI key="STATISTICS_VALID_PERCENT">100</MDI>
    </Metadata>
  </PAMRasterBand>
</PAMDataset>
